{"connected": true, "armed": false, "mode": "STABILIZE", "lat": 33.6458611, "lon": -117.8427498, "alt_rel": 0.005, "alt_abs": 25.08, "heading": 303.48, "vx": 0.0, "vy": 0.02, "vz": 0.0, "airspeed": 0.023331714794039726, "groundspeed": 0.023330992087721825, "battery_voltage": 12.6, "battery_remaining": 0, "battery_current": 0.0, "gps_fix_type": 0, "satellites_visible": 0, "hdop": 99.99, "system_status": 3, "pitch": 0.07305769105422656, "roll": 0.050769439765992776, "home_lat": null, "home_lon": null, "ekf_flags": 0, "ekf_status_report": "EKF INIT", "last_heartbeat_time": 1748493871.4286397, "heartbeat_count": 72}